topsis_pypi/102203103.py
topsis_pypi/__init__.py
topsis_Krishnansh_Verma_102203103-1.0.1.dist-info/LICENSE
topsis_Krishnansh_Verma_102203103-1.0.1.dist-info/METADATA
topsis_Krishnansh_Verma_102203103-1.0.1.dist-info/WHEEL
topsis_Krishnansh_Verma_102203103-1.0.1.dist-info/entry_points.txt
topsis_Krishnansh_Verma_102203103-1.0.1.dist-info/top_level.txt
topsis_Krishnansh_Verma_102203103-1.0.1.dist-info/RECORD
