Metadata-Version: 2.2
Name: topsis-Krishnansh_Verma_102203103
Version: 1.0.1
Summary: This Python package implements the TOPSIS (Technique for Order of Preference by Similarity to Ideal Solution) method for rank calculation. It helps in ranking alternatives based on multiple criteria by determining their proximity to the ideal and negative-ideal solutions. The package is efficient and easy to use for decision-making tasks.
Author: Krishnansh Verma
Classifier: Programming Language :: Python :: 3
Classifier: License :: OSI Approved :: MIT License
Classifier: Operating System :: OS Independent
Requires-Python: >=3.6
License-File: LICENSE
Requires-Dist: numpy
Requires-Dist: pandas
Dynamic: author
Dynamic: classifier
Dynamic: description
Dynamic: description-content-type
Dynamic: requires-dist
Dynamic: requires-python
Dynamic: summary
